HW5/Problem3/button_sync.v
`timescale 1ns/1ps
module button_sync (b_o, clk, rst_n, b_i); 
    input   clk, rst_n, b_i;
    output reg  b_o;      

    localparam S0_WAIT_PRESS   = 2'b00;
    localparam S1_PULSE        = 2'b01;
    localparam S2_WAIT_RELEASE = 2'b10;

    reg [1:0] state, next_state;
    always @(posedge clk or negedge rst_n) begin : state_reg
        if (!rst_n)
            state <= S0_WAIT_PRESS;
        else
            state <= next_state;
    end
    always @(*) begin : next_state_logic
        next_state = state;
        b_o        = 1'b0;
        case (state)
            S0_WAIT_PRESS: begin
                b_o = 1'b0;
                if (b_i == 1'b1)
                    next_state = S1_PULSE;
                else
                    next_state = S0_WAIT_PRESS;
            end
            S1_PULSE: begin
                b_o        = 1'b1;
                next_state = S2_WAIT_RELEASE;  
            end
            S2_WAIT_RELEASE: begin
                b_o = 1'b0;
                if (b_i == 1'b0)
                    next_state = S0_WAIT_PRESS;   
                else
                    next_state = S2_WAIT_RELEASE; 
            end
            default: begin
                b_o        = 1'b0;
                next_state = S0_WAIT_PRESS;
            end
        endcase
    end
endmodule

HW5/Problem3/button_sync_tb.v
`timescale 1ns/1ps
module button_sync_tb;

    reg clk;
    reg rst_n;
    reg b_i;
    wire b_o;

    button_sync dut (
        .clk  (clk),
        .rst_n(rst_n),
        .b_i  (b_i),
        .b_o  (b_o)
    );

    initial begin
        clk = 1'b0;
        forever #5 clk = ~clk;   // 5ns high, 5ns low
    end

    initial begin
        rst_n = 1'b0;
        b_i   = 1'b0;
        #20;
        rst_n = 1'b1;
        #7  b_i = 1'b1;  
        #30 b_i = 1'b0;  
        #20;
        #3  b_i = 1'b1;
        #50 b_i = 1'b0;

        #15 b_i = 1'b1;
        #10 b_i = 1'b0;

        #30;
        $finish;
    end

    integer cycle = 0;
    always @(posedge clk) begin
        cycle = cycle + 1;
        $display("T=%0t ns, cycle=%0d, b_i=%b, b_o=%b",
                 $time, cycle, b_i, b_o);
    end

endmodule

HW5/Problem3/button_sync_tb.vcd
$date
    Nov 18, 2025  00:55:24
$end
$version
    TOOL:	xmsim(64)	18.09-s011
$end
$timescale
    1 ps
$end

$scope module button_sync_tb $end
$var reg       1 !    clk $end
$var reg       1 "    rst_n $end
$var reg       1 #    b_i $end
$var wire      1 $    b_o  $end
$var integer  32 %    cycle $end

$scope module dut $end
$var wire      1 &    clk  $end
$var wire      1 '    rst_n  $end
$var wire      1 (    b_i  $end
$var reg       1 )    b_o $end
$var parameter  2 *    S0_WAIT_PRESS $end
$var parameter  2 +    S1_PULSE $end
$var parameter  2 ,    S2_WAIT_RELEASE $end
$var reg       2 -    state [1:0] $end
$var reg       2 .    next_state [1:0] $end
$upscope $end

$upscope $end

$enddefinitions $end
$dumpvars
b10 ,
b1 +
b0 *
0!
0"
0#
0$
b0 %
0&
0'
0(
0)
b0 -
b0 .
$end
#5000
1!
b1 %
1&
#10000
0!
0&
#15000
1!
b10 %
1&
#20000
1"
0!
0&
1'
#25000
1!
b11 %
1&
#27000
1#
1(
b1 .
#30000
0!
0&
#35000
1!
b100 %
1&
b1 -
1)
b10 .
1$
#40000
0!
0&
#45000
1!
b101 %
1&
b10 -
0)
0$
#50000
0!
0&
#55000
1!
b110 %
1&
#57000
0#
0(
b0 .
#60000
0!
0&
#65000
1!
b111 %
1&
b0 -
#70000
0!
0&
#75000
1!
b1000 %
1&
#80000
0!
1#
1(
0&
b1 .
#85000
1!
b1001 %
1&
b1 -
1)
b10 .
1$
#90000
0!
0&
#95000
1!
b1010 %
1&
b10 -
0)
0$
#100000
0!
0&
#105000
1!
b1011 %
1&
#110000
0!
0&
#115000
1!
b1100 %
1&
#120000
0!
0&
#125000
1!
b1101 %
1&
#130000
0#
0!
0&
0(
b0 .
#135000
1!
b1110 %
1&
b0 -
#140000
0!
0&
#145000
1#
1!
b1111 %
1&
1(
b1 .
#150000
0!
0&
#155000
0#
1!
b10000 %
1&
0(
b0 .
b1 -
b1 .
1)
b10 .
1$
#160000
0!
0&
#165000
1!
b10001 %
1&
b10 -
0)
b0 .
0$
#170000
0!
0&
#175000
1!
b10010 %
1&
b0 -
