HW2/problem3.v
`timescale 1ns/1ps

module decoder_2to4(I, POL, Y);
    input [1:0] I;     // 2-bit input
    input POL;         // polarity control
    output [3:0] Y;    // 4-bit output

    wire [1:0] inv_I;
    wire [3:0] and_out;

    assign inv_I = ~I;
    assign and_out[0] = inv_I[0] & inv_I[1] ;
    assign and_out[1] = I[0] & inv_I[1];
    assign and_out[2] = inv_I[0] & I[1];
    assign and_out[3] = I[0] & I[1];

    assign Y = and_out ^ {4{~POL}};
endmodule

HW2/tb_problem3.v
`timescale 1ns/1ps
module tb_decoder_2to4;

  reg  [1:0] I;
  reg        POL;
  wire [3:0] Y;

  decoder_2to4 dut (
    .I  (I),
    .POL(POL),
    .Y  (Y)
  );

  integer vec;
  initial begin
    // VCD dump for waveform
    $dumpfile("decoder_2to4_tb.vcd");
    $dumpvars(0, tb_decoder_2to4);
    // Header
    $display(" time | POL I1 I0 ||  Y3 Y2 Y1 Y0");
    $display("-----------------------------------");

    // Sweep all inputs {POL,I} = 3'b000 .. 3'b111
    for (vec = 0; vec < 8; vec = vec + 1) begin
      {POL, I} = vec[2:0];
      #1; // allow signal settle
      $display("%4t |  %0b   %0b  %0b ||   %0b  %0b  %0b  %0b",
               $time, POL, I[1], I[0], Y[3], Y[2], Y[1], Y[0]);
    end
  end
endmodule

HW2/decoder_2to4_tb.vcd
$date
    Oct 17, 2025  16:55:04
$end
$version
    TOOL:	xmsim	18.09-s011
$end
$timescale
    1 ps
$end

$scope module tb_decoder_2to4 $end
$var reg       2 !    I [1:0] $end
$var reg       1 "    POL $end
$var wire      4 #    Y [3:0] $end
$var integer  32 $    vec $end

$scope module dut $end
$var wire      2 %    I [1:0] $end
$var wire      1 &    POL  $end
$var wire      4 #    Y [3:0] $end
$var wire      2 '    inv_I [1:0] $end
$var wire      4 (    and_out [3:0] $end
$upscope $end

$upscope $end

$enddefinitions $end
$dumpvars
b0 !
0"
b1110 #
b0 $
b0 %
0&
b11 '
b1 (
$end
#1000
b1 $
b1 !
b1 %
b11 (
b10 '
b10 (
b1100 #
b1101 #
#2000
b10 $
b10 !
b10 %
b0 (
b1 '
b100 (
b1111 #
b1011 #
#3000
b11 $
b11 !
b11 %
b1100 (
b0 '
b1000 (
b11 #
b111 #
#4000
b100 $
b0 !
1"
1&
b0 %
b0 (
b11 '
b1000 #
b1 (
b0 #
b1 #
#5000
b101 $
b1 !
b1 %
b11 (
b10 '
b10 (
b11 #
b10 #
#6000
b110 $
b10 !
b10 %
b0 (
b1 '
b100 (
b0 #
b100 #
#7000
b111 $
b11 !
b11 %
b1100 (
b0 '
b1000 (
b1100 #
b1000 #
#8000
b1000 $
