HW2/problem4_FA.v
`timescale 1ns/1ps

module FA(A, B, Cin, S, Cout);
    input A, B, Cin;
    output S, Cout;

    wire xorAB, andAB, andAC, andBC;

    assign xorAB = A ^ B;
    assign andAB = A & B;
    assign andAC = A & Cin;
    assign andBC = B & Cin;

    assign S = xorAB ^ Cin;
    assign Cout = andAB | andAC | andBC;

endmodule

HW2/problem4_RCA4.v
`timescale 1ns/1ps
module RCA4(A, B, Cin, S, Cout);
    input [3:0] A, B;
    input Cin;
    output [3:0] S;
    output Cout;

    wire [3:0] C;

    FA FA0(A[0], B[0], Cin, S[0], C[0]);
    FA FA1(A[1], B[1], C[0], S[1], C[1]);
    FA FA2(A[2], B[2], C[1], S[2], C[2]);
    FA FA3(A[3], B[3], C[2], S[3], C[3]);
    assign Cout = C[3];
endmodule

HW2/tb_problem4_RCA4_old.v
`timescale 1ns/1ps

module tb_RCA4;

  // DUT inputs/outputs
  reg  [3:0] A, B;
  reg        Cin;
  wire [3:0] S;
  wire       Cout;

  // Instantiate RCA4
  RCA4 dut (
    .A(A),
    .B(B),
    .Cin(Cin),
    .S(S),
    .Cout(Cout)
  );

  // Reference model
  reg [4:0] expected;
  integer i, j, k;
  integer errors;

  initial begin
    errors = 0;

    // Generate waveform
    $dumpfile("RCA4_tb.vcd");
    $dumpvars(0, tb_RCA4);

    // Header
    $display(" time | Cin |   A    +   B   |  S Cout | Expected | Result");
    $display("----------------------------------------------------------");

    // Test all combinations of A, B, Cin
    for (i = 0; i < 16; i = i + 1) begin
      for (j = 0; j < 16; j = j + 1) begin
        for (k = 0; k < 2; k = k + 1) begin
          A = i; B = j; Cin = k;
          #1;
          expected = A + B + Cin;

          $display("%4t |  %b  | %2d(%b) + %2d(%b) | %2d(%b)  %b  |  %2d(%b)   | %s",
            $time, Cin, A, A, B, B, S, S, Cout,
            expected[3:0], expected[3:0],
            (S === expected[3:0] && Cout === expected[4]) ? "PASS" : "FAIL");

          if (S !== expected[3:0] || Cout !== expected[4])
            errors = errors + 1;
        end
      end
    end

    // Test result
    if (errors == 0)
      $display("✅ All tests PASSED!");
    else
      $display("❌ TEST FAILED: %0d errors found.", errors);

    $finish;
  end

endmodule

HW2/RCA4_tb.vcd
$date
    Oct 17, 2025  17:11:52
$end
$version
    TOOL:	xmsim	18.09-s011
$end
$timescale
    1 ps
$end

$scope module tb_RCA4 $end
$var reg       4 !    A [3:0] $end
$var reg       4 "    B [3:0] $end
$var reg       1 #    Cin $end
$var wire      1 $    S [3] $end
$var wire      1 %    S [2] $end
$var wire      1 &    S [1] $end
$var wire      1 '    S [0] $end
$var wire      1 (    Cout  $end
$var reg       5 )    expected [4:0] $end
$var integer  32 *    i $end
$var integer  32 +    j $end
$var integer  32 ,    k $end
$var integer  32 -    errors $end

$scope module dut $end
$var wire      1 .    A [3] $end
$var wire      1 /    A [2] $end
$var wire      1 0    A [1] $end
$var wire      1 1    A [0] $end
$var wire      1 2    B [3] $end
$var wire      1 3    B [2] $end
$var wire      1 4    B [1] $end
$var wire      1 5    B [0] $end
$var wire      1 6    Cin  $end
$var wire      1 $    S [3] $end
$var wire      1 %    S [2] $end
$var wire      1 &    S [1] $end
$var wire      1 '    S [0] $end
$var wire      1 (    Cout  $end
$var wire      1 7    C [3] $end
$var wire      1 8    C [2] $end
$var wire      1 9    C [1] $end
$var wire      1 :    C [0] $end

$scope module FA0 $end
$var wire      1 1    A  $end
$var wire      1 5    B  $end
$var wire      1 6    Cin  $end
$var wire      1 '    S  $end
$var wire      1 :    Cout  $end
$var wire      1 ;    xorAB  $end
$var wire      1 <    andAB  $end
$var wire      1 =    andAC  $end
$var wire      1 >    andBC  $end
$upscope $end


$scope module FA1 $end
$var wire      1 0    A  $end
$var wire      1 4    B  $end
$var wire      1 :    Cin  $end
$var wire      1 &    S  $end
$var wire      1 9    Cout  $end
$var wire      1 ?    xorAB  $end
$var wire      1 @    andAB  $end
$var wire      1 A    andAC  $end
$var wire      1 B    andBC  $end
$upscope $end


$scope module FA2 $end
$var wire      1 /    A  $end
$var wire      1 3    B  $end
$var wire      1 9    Cin  $end
$var wire      1 %    S  $end
$var wire      1 8    Cout  $end
$var wire      1 C    xorAB  $end
$var wire      1 D    andAB  $end
$var wire      1 E    andAC  $end
$var wire      1 F    andBC  $end
$upscope $end


$scope module FA3 $end
$var wire      1 .    A  $end
$var wire      1 2    B  $end
$var wire      1 8    Cin  $end
$var wire      1 $    S  $end
$var wire      1 7    Cout  $end
$var wire      1 G    xorAB  $end
$var wire      1 H    andAB  $end
$var wire      1 I    andAC  $end
$var wire      1 J    andBC  $end
$upscope $end

$upscope $end

$upscope $end

$enddefinitions $end
$dumpvars
b0 !
b0 "
0#
0$
0%
0&
0'
0(
bx )
b0 *
b0 +
b0 ,
b0 -
0.
0/
00
01
02
03
04
05
06
07
08
09
0:
0;
0<
0=
0>
0?
0@
0A
0B
0C
0D
0E
0F
0G
0H
0I
0J
$end
#1000
b0 )
b1 ,
1#
16
1'
#2000
b1 )
b10 ,
b1 +
b0 ,
b1 "
0#
06
15
1;
#3000
b1 ,
1#
16
1>
0'
1:
1&
#4000
b10 )
b10 ,
b10 +
b0 ,
b10 "
0#
06
14
05
0;
0B
1?
0>
0:
09
0%
#5000
b1 ,
1#
16
1'
#6000
b11 )
b10 ,
b11 +
b0 ,
b11 "
0#
06
15
1;
#7000
b1 ,
1#
16
1>
0'
1:
1B
0&
19
1%
#8000
b100 )
b10 ,
b100 +
b0 ,
b100 "
0#
06
13
04
05
0;
0B
0?
0F
1C
0>
0:
1%
08
09
0$
#9000
b1 ,
1#
16
1'
#10000
b101 )
b10 ,
b101 +
b0 ,
b101 "
0#
06
15
1;
#11000
b1 ,
1#
16
1>
0'
1:
1&
#12000
b110 )
b10 ,
b110 +
b0 ,
b110 "
0#
06
14
05
0;
0B
1?
0>
0:
09
0F
1%
08
0$
#13000
b1 ,
1#
16
1'
#14000
b111 )
b10 ,
b111 +
b0 ,
b111 "
0#
06
15
1;
#15000
b1 ,
1#
16
1>
0'
1:
1B
0&
19
1F
0%
18
1$
#16000
b1000 )
b10 ,
b1000 +
b0 ,
b1000 "
0#
06
12
03
04
05
0;
0B
0?
0F
0C
0J
1G
0>
0:
1$
07
0%
08
09
0(
#17000
b1 ,
1#
16
1'
#18000
b1001 )
b10 ,
b1001 +
b0 ,
b1001 "
0#
06
15
1;
#19000
b1 ,
1#
16
1>
0'
1:
1&
#20000
b1010 )
b10 ,
b1010 +
b0 ,
b1010 "
0#
06
14
05
0;
0B
1?
0>
0:
09
0%
#21000
b1 ,
1#
16
1'
#22000
b1011 )
b10 ,
b1011 +
b0 ,
b1011 "
0#
06
15
1;
#23000
b1 ,
1#
16
1>
0'
1:
1B
0&
19
1%
#24000
b1100 )
b10 ,
b1100 +
b0 ,
b1100 "
0#
06
13
04
05
0;
0B
0?
0F
1C
0>
0:
1%
08
09
0J
1$
07
0(
#25000
b1 ,
1#
16
1'
#26000
b1101 )
b10 ,
b1101 +
b0 ,
b1101 "
0#
06
15
1;
#27000
b1 ,
1#
16
1>
0'
1:
1&
#28000
b1110 )
b10 ,
b1110 +
b0 ,
b1110 "
0#
06
14
05
0;
0B
1?
0>
0:
09
0F
1%
08
0J
1$
07
0(
#29000
b1 ,
1#
16
1'
#30000
b1111 )
b10 ,
b1111 +
b0 ,
b1111 "
0#
06
15
1;
#31000
b1 ,
1#
16
1>
0'
1:
1B
0&
19
1F
0%
18
1J
0$
17
1(
#32000
b10000 )
b10 ,
b10000 +
b1 *
b0 +
b0 ,
b1 !
b0 "
0#
06
02
03
04
05
11
0B
0?
0F
0C
0J
0G
0>
1'
0:
0$
07
0%
08
09
0(
#33000
b1 )
b1 ,
1#
16
1=
0'
1:
1&
#34000
b10 )
b10 ,
b1 +
b0 ,
b1 "
0#
06
15
1<
0;
0=
#35000
b1 ,
1#
16
1>
1=
1'
#36000
b11 )
b10 ,
b10 +
b0 ,
b10 "
0#
06
14
05
0<
1;
0B
1?
0>
0=
0:
09
0%
#37000
b1 ,
1#
16
1=
0'
1:
1B
0&
19
1%
#38000
b100 )
b10 ,
b11 +
b0 ,
b11 "
0#
06
15
1<
0;
0=
#39000
b1 ,
1#
16
1>
1=
1'
#40000
b101 )
b10 ,
b100 +
b0 ,
b100 "
0#
06
13
04
05
0<
1;
0B
0?
0F
1C
0>
0=
0:
1%
08
09
0$
#41000
b1 ,
1#
16
1=
0'
1:
1&
#42000
b110 )
b10 ,
b101 +
b0 ,
b101 "
0#
06
15
1<
0;
0=
#43000
b1 ,
1#
16
1>
1=
1'
#44000
b111 )
b10 ,
b110 +
b0 ,
b110 "
0#
06
14
05
0<
1;
0B
1?
0>
0=
0:
09
0F
1%
08
0$
#45000
b1 ,
1#
16
1=
0'
1:
1B
0&
19
1F
0%
18
1$
#46000
b1000 )
b10 ,
b111 +
b0 ,
b111 "
0#
06
15
1<
0;
0=
#47000
b1 ,
1#
16
1>
1=
1'
#48000
b1001 )
b10 ,
b1000 +
b0 ,
b1000 "
0#
06
12
03
04
05
0<
1;
0B
0?
0F
0C
0J
1G
0>
0=
0:
1$
07
0%
08
09
0(
#49000
b1 ,
1#
16
1=
0'
1:
1&
#50000
b1010 )
b10 ,
b1001 +
b0 ,
b1001 "
0#
06
15
1<
0;
0=
#51000
b1 ,
1#
16
1>
1=
1'
#52000
b1011 )
b10 ,
b1010 +
b0 ,
b1010 "
0#
06
14
05
0<
1;
0B
1?
0>
0=
0:
09
0%
#53000
b1 ,
1#
16
1=
0'
1:
1B
0&
19
1%
#54000
b1100 )
b10 ,
b1011 +
b0 ,
b1011 "
0#
06
15
1<
0;
0=
#55000
b1 ,
1#
16
1>
1=
1'
#56000
b1101 )
b10 ,
b1100 +
b0 ,
b1100 "
0#
06
13
04
05
0<
1;
0B
0?
0F
1C
0>
0=
0:
1%
08
09
0J
1$
07
0(
#57000
b1 ,
1#
16
1=
0'
1:
1&
#58000
b1110 )
b10 ,
b1101 +
b0 ,
b1101 "
0#
06
15
1<
0;
0=
#59000
b1 ,
1#
16
1>
1=
1'
#60000
b1111 )
b10 ,
b1110 +
b0 ,
b1110 "
0#
06
14
05
0<
1;
0B
1?
0>
0=
0:
09
0F
1%
08
0J
1$
07
0(
#61000
b1 ,
1#
16
1=
0'
1:
1B
0&
19
1F
0%
18
1J
0$
17
1(
#62000
b10000 )
b10 ,
b1111 +
b0 ,
b1111 "
0#
06
15
1<
0;
0=
#63000
b1 ,
1#
16
1>
1=
1'
#64000
b10001 )
b10 ,
b10000 +
b10 *
b0 +
b0 ,
b10 !
b0 "
0#
06
02
03
04
05
10
01
0A
0<
0B
0F
0C
0J
0G
0>
0=
0'
0:
0$
07
0%
08
0(
1&
09
#65000
b10 )
b1 ,
1#
16
1'
#66000
b11 )
b10 ,
b1 +
b0 ,
b1 "
0#
06
15
1;
#67000
b1 ,
1#
16
1>
0'
1:
1A
0&
19
1%
#68000
b100 )
b10 ,
b10 +
b0 ,
b10 "
0#
06
14
05
0;
1@
0B
0?
0>
0:
0A
#69000
b1 ,
1#
16
1'
#70000
b101 )
b10 ,
b11 +
b0 ,
b11 "
0#
06
15
1;
#71000
b1 ,
1#
16
1>
0'
1:
1B
1A
1&
#72000
b110 )
b10 ,
b100 +
b0 ,
b100 "
0#
06
13
04
05
0;
0@
0B
1?
0F
1C
0>
0:
1%
08
0$
0A
09
#73000
b1 ,
1#
16
1'
#74000
b111 )
b10 ,
b101 +
b0 ,
b101 "
0#
06
15
1;
#75000
b1 ,
1#
16
1>
0'
1:
1A
0&
19
1F
0%
18
1$
#76000
b1000 )
b10 ,
b110 +
b0 ,
b110 "
0#
06
14
05
0;
1@
0B
0?
0>
0:
0A
#77000
b1 ,
1#
16
1'
#78000
b1001 )
b10 ,
b111 +
b0 ,
b111 "
0#
06
15
1;
#79000
b1 ,
1#
16
1>
0'
1:
1B
1A
1&
#80000
b1010 )
b10 ,
b1000 +
b0 ,
b1000 "
0#
06
12
03
04
05
0;
0@
0B
1?
0F
0C
0J
1G
0>
0:
1$
07
0%
08
0(
0A
09
#81000
b1 ,
1#
16
1'
#82000
b1011 )
b10 ,
b1001 +
b0 ,
b1001 "
0#
06
15
1;
#83000
b1 ,
1#
16
1>
0'
1:
1A
0&
19
1%
#84000
b1100 )
b10 ,
b1010 +
b0 ,
b1010 "
0#
06
14
05
0;
1@
0B
0?
0>
0:
0A
#85000
b1 ,
1#
16
1'
#86000
b1101 )
b10 ,
b1011 +
b0 ,
b1011 "
0#
06
15
1;
#87000
b1 ,
1#
16
1>
0'
1:
1B
1A
1&
#88000
b1110 )
b10 ,
b1100 +
b0 ,
b1100 "
0#
06
13
04
05
0;
0@
0B
1?
0F
1C
0>
0:
1%
08
0J
1$
0A
09
07
0(
#89000
b1 ,
1#
16
1'
#90000
b1111 )
b10 ,
b1101 +
b0 ,
b1101 "
0#
06
15
1;
#91000
b1 ,
1#
16
1>
0'
1:
1A
0&
19
1F
0%
18
1J
0$
17
1(
#92000
b10000 )
b10 ,
b1110 +
b0 ,
b1110 "
0#
06
14
05
0;
1@
0B
0?
0>
0:
0A
#93000
b1 ,
1#
16
1'
#94000
b10001 )
b10 ,
b1111 +
b0 ,
b1111 "
0#
06
15
1;
#95000
b1 ,
1#
16
1>
0'
1:
1B
1A
1&
#96000
b10010 )
b10 ,
b10000 +
b11 *
b0 +
b0 ,
b11 !
b0 "
0#
06
02
03
04
05
11
0@
0B
1?
0F
0C
0J
0G
0>
1'
0:
0$
07
0%
08
0(
0A
09
#97000
b11 )
b1 ,
1#
16
1=
0'
1:
1A
0&
19
1%
#98000
b100 )
b10 ,
b1 +
b0 ,
b1 "
0#
06
15
1<
0;
0=
#99000
b1 ,
1#
16
1>
1=
1'
#100000
b101 )
b10 ,
b10 +
b0 ,
b10 "
0#
06
14
05
0<
1;
1@
0B
0?
0>
0=
0:
0A
#101000
b1 ,
1#
16
1=
0'
1:
1B
1A
1&
#102000
b110 )
b10 ,
b11 +
b0 ,
b11 "
0#
06
15
1<
0;
0=
#103000
b1 ,
1#
16
1>
1=
1'
#104000
b111 )
b10 ,
b100 +
b0 ,
b100 "
0#
06
13
04
05
0<
1;
0@
0B
1?
0F
1C
0>
0=
0:
1%
08
0$
0A
09
#105000
b1 ,
1#
16
1=
0'
1:
1A
0&
19
1F
0%
18
1$
#106000
b1000 )
b10 ,
b101 +
b0 ,
b101 "
0#
06
15
1<
0;
0=
#107000
b1 ,
1#
16
1>
1=
1'
#108000
b1001 )
b10 ,
b110 +
b0 ,
b110 "
0#
06
14
05
0<
1;
1@
0B
0?
0>
0=
0:
0A
#109000
b1 ,
1#
16
1=
0'
1:
1B
1A
1&
#110000
b1010 )
b10 ,
b111 +
b0 ,
b111 "
0#
06
15
1<
0;
0=
#111000
b1 ,
1#
16
1>
1=
1'
#112000
b1011 )
b10 ,
b1000 +
b0 ,
b1000 "
0#
06
12
03
04
05
0<
1;
0@
0B
1?
0F
0C
0J
1G
0>
0=
0:
1$
07
0%
08
0(
0A
09
#113000
b1 ,
1#
16
1=
0'
1:
1A
0&
19
1%
#114000
b1100 )
b10 ,
b1001 +
b0 ,
b1001 "
0#
06
15
1<
0;
0=
#115000
b1 ,
1#
16
1>
1=
1'
#116000
b1101 )
b10 ,
b1010 +
b0 ,
b1010 "
0#
06
14
05
0<
1;
1@
0B
0?
0>
0=
0:
0A
#117000
b1 ,
1#
16
1=
0'
1:
1B
1A
1&
#118000
b1110 )
b10 ,
b1011 +
b0 ,
b1011 "
0#
06
15
1<
0;
0=
#119000
b1 ,
1#
16
1>
1=
1'
#120000
b1111 )
b10 ,
b1100 +
b0 ,
b1100 "
0#
06
13
04
05
0<
1;
0@
0B
1?
0F
1C
0>
0=
0:
1%
08
0J
1$
0A
09
07
0(
#121000
b1 ,
1#
16
1=
0'
1:
1A
0&
19
1F
0%
18
1J
0$
17
1(
#122000
b10000 )
b10 ,
b1101 +
b0 ,
b1101 "
0#
06
15
1<
0;
0=
#123000
b1 ,
1#
16
1>
1=
1'
#124000
b10001 )
b10 ,
b1110 +
b0 ,
b1110 "
0#
06
14
05
0<
1;
1@
0B
0?
0>
0=
0:
0A
#125000
b1 ,
1#
16
1=
0'
1:
1B
1A
1&
#126000
b10010 )
b10 ,
b1111 +
b0 ,
b1111 "
0#
06
15
1<
0;
0=
#127000
b1 ,
1#
16
1>
1=
1'
#128000
b10011 )
b10 ,
b10000 +
b100 *
b0 +
b0 ,
b100 !
b0 "
0#
06
02
03
04
05
1/
00
01
0A
0E
0<
0@
0B
0F
0J
0G
0>
0=
0'
0:
0$
07
09
1%
0(
0&
08
#129000
b100 )
b1 ,
1#
16
1'
#130000
b101 )
b10 ,
b1 +
b0 ,
b1 "
0#
06
15
1;
#131000
b1 ,
1#
16
1>
0'
1:
1&
#132000
b110 )
b10 ,
b10 +
b0 ,
b10 "
0#
06
14
05
0;
0B
1?
0>
0:
09
0E
1%
08
0$
#133000
b1 ,
1#
16
1'
#134000
b111 )
b10 ,
b11 +
b0 ,
b11 "
0#
06
15
1;
#135000
b1 ,
1#
16
1>
0'
1:
1B
0&
19
1E
0%
18
1$
#136000
b1000 )
b10 ,
b100 +
b0 ,
b100 "
0#
06
13
04
05
0;
0B
0?
1D
0F
0C
0>
0:
0%
09
0E
#137000
b1 ,
1#
16
1'
#138000
b1001 )
b10 ,
b101 +
b0 ,
b101 "
0#
06
15
1;
#139000
b1 ,
1#
16
1>
0'
1:
1&
#140000
b1010 )
b10 ,
b110 +
b0 ,
b110 "
0#
06
14
05
0;
0B
1?
0>
0:
09
0F
0E
0%
#141000
b1 ,
1#
16
1'
#142000
b1011 )
b10 ,
b111 +
b0 ,
b111 "
0#
06
15
1;
#143000
b1 ,
1#
16
1>
0'
1:
1B
0&
19
1F
1E
1%
#144000
b1100 )
b10 ,
b1000 +
b0 ,
b1000 "
0#
06
12
03
04
05
0;
0B
0?
0D
0F
1C
0J
1G
0>
0:
1$
07
1%
09
0E
0(
08
#145000
b1 ,
1#
16
1'
#146000
b1101 )
b10 ,
b1001 +
b0 ,
b1001 "
0#
06
15
1;
#147000
b1 ,
1#
16
1>
0'
1:
1&
#148000
b1110 )
b10 ,
b1010 +
b0 ,
b1010 "
0#
06
14
05
0;
0B
1?
0>
0:
09
0E
1%
08
0J
1$
07
0(
#149000
b1 ,
1#
16
1'
#150000
b1111 )
b10 ,
b1011 +
b0 ,
b1011 "
0#
06
15
1;
#151000
b1 ,
1#
16
1>
0'
1:
1B
0&
19
1E
0%
18
1J
0$
17
1(
#152000
b10000 )
b10 ,
b1100 +
b0 ,
b1100 "
0#
06
13
04
05
0;
0B
0?
1D
0F
0C
0>
0:
0%
09
0E
#153000
b1 ,
1#
16
1'
#154000
b10001 )
b10 ,
b1101 +
b0 ,
b1101 "
0#
06
15
1;
#155000
b1 ,
1#
16
1>
0'
1:
1&
#156000
b10010 )
b10 ,
b1110 +
b0 ,
b1110 "
0#
06
14
05
0;
0B
1?
0>
0:
09
0F
0E
0%
#157000
b1 ,
1#
16
1'
#158000
b10011 )
b10 ,
b1111 +
b0 ,
b1111 "
0#
06
15
1;
#159000
b1 ,
1#
16
1>
0'
1:
1B
0&
19
1F
1E
1%
#160000
b10100 )
b10 ,
b10000 +
b101 *
b0 +
b0 ,
b101 !
b0 "
0#
06
02
03
04
05
11
0B
0?
0D
0F
1C
0J
0G
0>
1'
0:
0$
07
1%
09
0E
0(
08
#161000
b101 )
b1 ,
1#
16
1=
0'
1:
1&
#162000
b110 )
b10 ,
b1 +
b0 ,
b1 "
0#
06
15
1<
0;
0=
#163000
b1 ,
1#
16
1>
1=
1'
#164000
b111 )
b10 ,
b10 +
b0 ,
b10 "
0#
06
14
05
0<
1;
0B
1?
0>
0=
0:
09
0E
1%
08
0$
#165000
b1 ,
1#
16
1=
0'
1:
1B
0&
19
1E
0%
18
1$
#166000
b1000 )
b10 ,
b11 +
b0 ,
b11 "
0#
06
15
1<
0;
0=
#167000
b1 ,
1#
16
1>
1=
1'
#168000
b1001 )
b10 ,
b100 +
b0 ,
b100 "
0#
06
13
04
05
0<
1;
0B
0?
1D
0F
0C
0>
0=
0:
0%
09
0E
#169000
b1 ,
1#
16
1=
0'
1:
1&
#170000
b1010 )
b10 ,
b101 +
b0 ,
b101 "
0#
06
15
1<
0;
0=
#171000
b1 ,
1#
16
1>
1=
1'
#172000
b1011 )
b10 ,
b110 +
b0 ,
b110 "
0#
06
14
05
0<
1;
0B
1?
0>
0=
0:
09
0F
0E
0%
#173000
b1 ,
1#
16
1=
0'
1:
1B
0&
19
1F
1E
1%
#174000
b1100 )
b10 ,
b111 +
b0 ,
b111 "
0#
06
15
1<
0;
0=
#175000
b1 ,
1#
16
1>
1=
1'
#176000
b1101 )
b10 ,
b1000 +
b0 ,
b1000 "
0#
06
12
03
04
05
0<
1;
0B
0?
0D
0F
1C
0J
1G
0>
0=
0:
1$
07
1%
09
0E
0(
08
#177000
b1 ,
1#
16
1=
0'
1:
1&
#178000
b1110 )
b10 ,
b1001 +
b0 ,
b1001 "
0#
06
15
1<
0;
0=
#179000
b1 ,
1#
16
1>
1=
1'
#180000
b1111 )
b10 ,
b1010 +
b0 ,
b1010 "
0#
06
14
05
0<
1;
0B
1?
0>
0=
0:
09
0E
1%
08
0J
1$
07
0(
#181000
b1 ,
1#
16
1=
0'
1:
1B
0&
19
1E
0%
18
1J
0$
17
1(
#182000
b10000 )
b10 ,
b1011 +
b0 ,
b1011 "
0#
06
15
1<
0;
0=
#183000
b1 ,
1#
16
1>
1=
1'
#184000
b10001 )
b10 ,
b1100 +
b0 ,
b1100 "
0#
06
13
04
05
0<
1;
0B
0?
1D
0F
0C
0>
0=
0:
0%
09
0E
#185000
b1 ,
1#
16
1=
0'
1:
1&
#186000
b10010 )
b10 ,
b1101 +
b0 ,
b1101 "
0#
06
15
1<
0;
0=
#187000
b1 ,
1#
16
1>
1=
1'
#188000
b10011 )
b10 ,
b1110 +
b0 ,
b1110 "
0#
06
14
05
0<
1;
0B
1?
0>
0=
0:
09
0F
0E
0%
#189000
b1 ,
1#
16
1=
0'
1:
1B
0&
19
1F
1E
1%
#190000
b10100 )
b10 ,
b1111 +
b0 ,
b1111 "
0#
06
15
1<
0;
0=
#191000
b1 ,
1#
16
1>
1=
1'
#192000
b10101 )
b10 ,
b10000 +
b110 *
b0 +
b0 ,
b110 !
b0 "
0#
06
02
03
04
05
10
01
0A
0<
0B
0D
0F
1C
0J
0G
0>
0=
0'
0:
0$
07
1%
0(
1&
09
0E
08
#193000
b110 )
b1 ,
1#
16
1'
#194000
b111 )
b10 ,
b1 +
b0 ,
b1 "
0#
06
15
1;
#195000
b1 ,
1#
16
1>
0'
1:
1A
0&
19
1E
0%
18
1$
#196000
b1000 )
b10 ,
b10 +
b0 ,
b10 "
0#
06
14
05
0;
1@
0B
0?
0>
0:
0A
#197000
b1 ,
1#
16
1'
#198000
b1001 )
b10 ,
b11 +
b0 ,
b11 "
0#
06
15
1;
#199000
b1 ,
1#
16
1>
0'
1:
1B
1A
1&
#200000
b1010 )
b10 ,
b100 +
b0 ,
b100 "
0#
06
13
04
05
0;
0@
0B
1?
1D
0F
0C
0>
0:
0%
0A
09
0E
#201000
b1 ,
1#
16
1'
#202000
b1011 )
b10 ,
b101 +
b0 ,
b101 "
0#
06
15
1;
#203000
b1 ,
1#
16
1>
0'
1:
1A
0&
19
1F
1E
1%
#204000
b1100 )
b10 ,
b110 +
b0 ,
b110 "
0#
06
14
05
0;
1@
0B
0?
0>
0:
0A
#205000
b1 ,
1#
16
1'
#206000
b1101 )
b10 ,
b111 +
b0 ,
b111 "
0#
06
15
1;
#207000
b1 ,
1#
16
1>
0'
1:
1B
1A
1&
#208000
b1110 )
b10 ,
b1000 +
b0 ,
b1000 "
0#
06
12
03
04
05
0;
0@
0B
1?
0D
0F
1C
0J
1G
0>
0:
1$
07
1%
0(
0A
09
0E
08
#209000
b1 ,
1#
16
1'
#210000
b1111 )
b10 ,
b1001 +
b0 ,
b1001 "
0#
06
15
1;
#211000
b1 ,
1#
16
1>
0'
1:
1A
0&
19
1E
0%
18
1J
0$
17
1(
#212000
b10000 )
b10 ,
b1010 +
b0 ,
b1010 "
0#
06
14
05
0;
1@
0B
0?
0>
0:
0A
#213000
b1 ,
1#
16
1'
#214000
b10001 )
b10 ,
b1011 +
b0 ,
b1011 "
0#
06
15
1;
#215000
b1 ,
1#
16
1>
0'
1:
1B
1A
1&
#216000
b10010 )
b10 ,
b1100 +
b0 ,
b1100 "
0#
06
13
04
05
0;
0@
0B
1?
1D
0F
0C
0>
0:
0%
0A
09
0E
#217000
b1 ,
1#
16
1'
#218000
b10011 )
b10 ,
b1101 +
b0 ,
b1101 "
0#
06
15
1;
#219000
b1 ,
1#
16
1>
0'
1:
1A
0&
19
1F
1E
1%
#220000
b10100 )
b10 ,
b1110 +
b0 ,
b1110 "
0#
06
14
05
0;
1@
0B
0?
0>
0:
0A
#221000
b1 ,
1#
16
1'
#222000
b10101 )
b10 ,
b1111 +
b0 ,
b1111 "
0#
06
15
1;
#223000
b1 ,
1#
16
1>
0'
1:
1B
1A
1&
#224000
b10110 )
b10 ,
b10000 +
b111 *
b0 +
b0 ,
b111 !
b0 "
0#
06
02
03
04
05
11
0@
0B
1?
0D
0F
1C
0J
0G
0>
1'
0:
0$
07
1%
0(
0A
09
0E
08
#225000
b111 )
b1 ,
1#
16
1=
0'
1:
1A
0&
19
1E
0%
18
1$
#226000
b1000 )
b10 ,
b1 +
b0 ,
b1 "
0#
06
15
1<
0;
0=
#227000
b1 ,
1#
16
1>
1=
1'
#228000
b1001 )
b10 ,
b10 +
b0 ,
b10 "
0#
06
14
05
0<
1;
1@
0B
0?
0>
0=
0:
0A
#229000
b1 ,
1#
16
1=
0'
1:
1B
1A
1&
#230000
b1010 )
b10 ,
b11 +
b0 ,
b11 "
0#
06
15
1<
0;
0=
#231000
b1 ,
1#
16
1>
1=
1'
#232000
b1011 )
b10 ,
b100 +
b0 ,
b100 "
0#
06
13
04
05
0<
1;
0@
0B
1?
1D
0F
0C
0>
0=
0:
0%
0A
09
0E
#233000
b1 ,
1#
16
1=
0'
1:
1A
0&
19
1F
1E
1%
#234000
b1100 )
b10 ,
b101 +
b0 ,
b101 "
0#
06
15
1<
0;
0=
#235000
b1 ,
1#
16
1>
1=
1'
#236000
b1101 )
b10 ,
b110 +
b0 ,
b110 "
0#
06
14
05
0<
1;
1@
0B
0?
0>
0=
0:
0A
#237000
b1 ,
1#
16
1=
0'
1:
1B
1A
1&
#238000
b1110 )
b10 ,
b111 +
b0 ,
b111 "
0#
06
15
1<
0;
0=
#239000
b1 ,
1#
16
1>
1=
1'
#240000
b1111 )
b10 ,
b1000 +
b0 ,
b1000 "
0#
06
12
03
04
05
0<
1;
0@
0B
1?
0D
0F
1C
0J
1G
0>
0=
0:
1$
07
1%
0(
0A
09
0E
08
#241000
b1 ,
1#
16
1=
0'
1:
1A
0&
19
1E
0%
18
1J
0$
17
1(
#242000
b10000 )
b10 ,
b1001 +
b0 ,
b1001 "
0#
06
15
1<
0;
0=
#243000
b1 ,
1#
16
1>
1=
1'
#244000
b10001 )
b10 ,
b1010 +
b0 ,
b1010 "
0#
06
14
05
0<
1;
1@
0B
0?
0>
0=
0:
0A
#245000
b1 ,
1#
16
1=
0'
1:
1B
1A
1&
#246000
b10010 )
b10 ,
b1011 +
b0 ,
b1011 "
0#
06
15
1<
0;
0=
#247000
b1 ,
1#
16
1>
1=
1'
#248000
b10011 )
b10 ,
b1100 +
b0 ,
b1100 "
0#
06
13
04
05
0<
1;
0@
0B
1?
1D
0F
0C
0>
0=
0:
0%
0A
09
0E
#249000
b1 ,
1#
16
1=
0'
1:
1A
0&
19
1F
1E
1%
#250000
b10100 )
b10 ,
b1101 +
b0 ,
b1101 "
0#
06
15
1<
0;
0=
#251000
b1 ,
1#
16
1>
1=
1'
#252000
b10101 )
b10 ,
b1110 +
b0 ,
b1110 "
0#
06
14
05
0<
1;
1@
0B
0?
0>
0=
0:
0A
#253000
b1 ,
1#
16
1=
0'
1:
1B
1A
1&
#254000
b10110 )
b10 ,
b1111 +
b0 ,
b1111 "
0#
06
15
1<
0;
0=
#255000
b1 ,
1#
16
1>
1=
1'
#256000
b10111 )
b10 ,
b10000 +
b1000 *
b0 +
b0 ,
b1000 !
b0 "
0#
06
02
03
04
05
1.
0/
00
01
0A
0E
0I
0<
0@
0B
0D
0F
0J
0>
0=
0'
0:
08
09
0%
1$
0&
07
0(
#257000
b1000 )
b1 ,
1#
16
1'
#258000
b1001 )
b10 ,
b1 +
b0 ,
b1 "
0#
06
15
1;
#259000
b1 ,
1#
16
1>
0'
1:
1&
#260000
b1010 )
b10 ,
b10 +
b0 ,
b10 "
0#
06
14
05
0;
0B
1?
0>
0:
09
0%
#261000
b1 ,
1#
16
1'
#262000
b1011 )
b10 ,
b11 +
b0 ,
b11 "
0#
06
15
1;
#263000
b1 ,
1#
16
1>
0'
1:
1B
0&
19
1%
#264000
b1100 )
b10 ,
b100 +
b0 ,
b100 "
0#
06
13
04
05
0;
0B
0?
0F
1C
0>
0:
1%
08
09
0I
1$
07
0(
#265000
b1 ,
1#
16
1'
#266000
b1101 )
b10 ,
b101 +
b0 ,
b101 "
0#
06
15
1;
#267000
b1 ,
1#
16
1>
0'
1:
1&
#268000
b1110 )
b10 ,
b110 +
b0 ,
b110 "
0#
06
14
05
0;
0B
1?
0>
0:
09
0F
1%
08
0I
1$
07
0(
#269000
b1 ,
1#
16
1'
#270000
b1111 )
b10 ,
b111 +
b0 ,
b111 "
0#
06
15
1;
#271000
b1 ,
1#
16
1>
0'
1:
1B
0&
19
1F
0%
18
1I
0$
17
1(
