HW6/p1/vredge.v
`timescale 1ns/1ps

module Vredge (clk, rst_n, X, EDGE, state_dbg);
    input   clk;
    input   rst_n;
    input   X;     
    output reg  EDGE;    
    output [1:0] state_dbg; 

    localparam [1:0] A = 2'b00, // stable-0
                     B = 2'b01, // 0->1 edge
                     C = 2'b10, // stable-1
                     D = 2'b11; // 1->0 edge

    reg [1:0] state, next;

    // State register
    always @(posedge clk or negedge rst_n) begin
        if (!rst_n)
            state <= A;
        else
            state <= next;
    end

    // Next-state 
    always @* begin
        case (state)
            A: next = (X ? B : A);    
            B: next = (X ? C : D);   
            C: next = (X ? C : D);    
            D: next = (X ? B : A);   
            default: next = A;
        endcase
    end

    // Registered output
    always @(posedge clk or negedge rst_n) begin
        if (!rst_n)
            EDGE <= 1'b0;
        else
            EDGE <= (next == B) || (next == D);
    end

    assign state_dbg = state;
endmodule

HW6/p1/vredge_tb_check.v
//==============================================================
// tb_vredge_check.v — self-checking testbench for registered EDGE
// Verifies: EDGE == (X_prev ^ X_prev2)
//==============================================================
`timescale 1ns/1ps

module tb_Vredge_check;
    reg  clk   = 0;
    reg  rst_n = 0;
    reg  X     = 0;
    wire EDGE;

    Vredge dut (.clk(clk), .rst_n(rst_n), .X(X), .EDGE(EDGE));

    always #5 clk = ~clk;

    initial begin
        $dumpfile("Vredge_check.vcd");
        $dumpvars(0, tb_Vredge_check);
    end

    // Store last two X values
    reg X_d1, X_d2;
    integer pass_cnt = 0;
    integer fail_cnt = 0;
    integer sample_cnt = 0;

    // Judge: check one-cycle delayed relation
    always @(posedge clk or negedge rst_n) begin
        if (!rst_n) begin
            X_d1 <= 0;
            X_d2 <= 0;
        end else begin
            sample_cnt = sample_cnt + 1;
            if (EDGE !== (X_d1 ^ X_d2)) begin
                fail_cnt = fail_cnt + 1;
                $display("[%0t] FAIL: X_d1=%0b X_d2=%0b expected EDGE=%0b got %0b",
                         $time, X_d1, X_d2, (X_d1 ^ X_d2), EDGE);
            end else begin
                pass_cnt = pass_cnt + 1;
            end
            // shift registers
            X_d2 <= X_d1;
            X_d1 <= X;
        end
    end

    // Reset sequence
    initial begin
        repeat (2) @(posedge clk);
        rst_n <= 1'b1;
    end

    // Drive X on negedge
    initial begin
        repeat (2) @(negedge clk); X <= 0;

        @(negedge clk); X <= 1;
        @(negedge clk); X <= 1;
        @(negedge clk); X <= 0;
        @(negedge clk); X <= 0;
        @(negedge clk); X <= 1;
        @(negedge clk); X <= 0;
        @(negedge clk); X <= 1;
        @(negedge clk); X <= 1;

        // Random stress
        repeat (40) begin
            @(negedge clk);
            X <= $urandom;
        end

        // Report summary
        repeat (3) @(posedge clk);
        $display("==== SELF-CHECK SUMMARY ====");
        $display("samples checked : %0d", sample_cnt);
        $display("pass            : %0d", pass_cnt);
        $display("fail            : %0d", fail_cnt);
        if (fail_cnt==0) $display("RESULT          : PASS");
        else             $display("RESULT          : FAIL");
        $finish;
    end
endmodule

HW6/p1/Vredge_check.vcd
$date
    Nov 11, 2025  20:52:41
$end
$version
    TOOL:	xmsim	18.09-s011
$end
$timescale
    1 ps
$end

$scope module tb_Vredge_check $end
$var reg       1 !    clk $end
$var reg       1 "    rst_n $end
$var reg       1 #    X $end
$var wire      1 $    EDGE  $end
$var reg       1 %    X_d1 $end
$var reg       1 &    X_d2 $end
$var integer  32 '    pass_cnt $end
$var integer  32 (    fail_cnt $end
$var integer  32 )    sample_cnt $end

$scope module dut $end
$var wire      1 *    clk  $end
$var wire      1 +    rst_n  $end
$var wire      1 ,    X  $end
$var reg       1 -    EDGE $end
$var wire      2 .    state_dbg [1:0] $end
$var parameter  2 /    A [1:0] $end
$var parameter  2 0    B [1:0] $end
$var parameter  2 1    C [1:0] $end
$var parameter  2 2    D [1:0] $end
$var reg       2 3    state [1:0] $end
$var reg       2 4    next [1:0] $end
$upscope $end

$upscope $end

$enddefinitions $end
$dumpvars
b11 2
b10 1
b1 0
b0 /
0!
0"
0#
0$
x%
x&
b0 '
b0 (
b0 )
0*
0+
0,
0-
b0 .
b0 3
b0 4
$end
#5000
1!
1*
0%
0&
#10000
0!
0*
#15000
1!
1*
1"
1+
#20000
0!
0*
#25000
1!
b1 )
b1 '
1*
#30000
0!
0*
1#
1,
b1 4
#35000
1!
b10 )
b10 '
1*
1%
b1 3
b10 4
b1 .
#40000
0!
0*
#45000
1!
b11 )
b1 (
1*
1&
b10 3
1-
1$
b10 .
#50000
0!
0*
0#
0,
b11 4
#55000
1!
b100 )
b10 (
1*
0%
b11 3
0-
b0 4
0$
b11 .
#60000
0!
0*
#65000
1!
b101 )
b11 (
1*
0&
b0 3
1-
1$
b0 .
#70000
0!
0*
1#
1,
b1 4
#75000
1!
b110 )
b100 (
1*
1%
b1 3
0-
b10 4
0$
b1 .
#80000
0!
0*
0#
0,
b11 4
#85000
1!
b111 )
b101 (
1*
1&
0%
b11 3
1-
b0 4
1$
b11 .
#90000
0!
0*
1#
1,
b1 4
#95000
1!
b1000 )
b11 '
1*
0&
1%
b1 3
b10 4
b1 .
#100000
0!
0*
#105000
1!
b1001 )
b100 '
1*
1&
b10 3
b10 .
#110000
0!
0*
0#
0,
b11 4
#115000
1!
b1010 )
b110 (
1*
0%
b11 3
0-
b0 4
0$
b11 .
#120000
0!
0*
#125000
1!
b1011 )
b111 (
1*
0&
b0 3
1-
1$
b0 .
#130000
0!
0*
#135000
1!
b1100 )
b1000 (
1*
0-
0$
#140000
0!
0*
1#
1,
b1 4
#145000
1!
b1101 )
b101 '
1*
1%
b1 3
b10 4
b1 .
#150000
0!
0*
#155000
1!
b1110 )
b1001 (
1*
1&
b10 3
1-
1$
b10 .
#160000
0!
0*
0#
0,
b11 4
#165000
1!
b1111 )
b1010 (
1*
0%
b11 3
0-
b0 4
0$
b11 .
#170000
0!
0*
#175000
1!
b10000 )
b1011 (
1*
0&
b0 3
1-
1$
b0 .
#180000
0!
0*
#185000
1!
b10001 )
b1100 (
1*
0-
0$
#190000
0!
0*
#195000
1!
b10010 )
b110 '
1*
#200000
0!
0*
1#
1,
b1 4
#205000
1!
b10011 )
b111 '
1*
1%
b1 3
b10 4
b1 .
#210000
0!
0*
0#
0,
b11 4
#215000
1!
b10100 )
b1101 (
1*
1&
0%
b11 3
1-
b0 4
1$
b11 .
#220000
0!
0*
#225000
1!
b10101 )
b1000 '
1*
0&
b0 3
b0 .
#230000
0!
0*
1#
1,
b1 4
#235000
1!
b10110 )
b1110 (
1*
1%
b1 3
0-
b10 4
0$
b1 .
#240000
0!
0*
#245000
1!
b10111 )
b1111 (
1*
1&
b10 3
1-
1$
b10 .
#250000
0!
0*
#255000
1!
b11000 )
b10000 (
1*
0-
0$
#260000
0!
0*
#265000
1!
b11001 )
b1001 '
1*
#270000
0!
0*
#275000
1!
b11010 )
b1010 '
1*
#280000
0!
0*
0#
0,
b11 4
#285000
1!
b11011 )
b1011 '
1*
0%
b11 3
b0 4
b11 .
#290000
0!
0*
1#
1,
b1 4
#295000
1!
b11100 )
b10001 (
1*
0&
1%
b1 3
1-
b10 4
1$
b1 .
#300000
0!
0*
#305000
1!
b11101 )
b1100 '
1*
1&
b10 3
b10 .
#310000
0!
0*
#315000
1!
b11110 )
b10010 (
1*
0-
0$
#320000
0!
0*
#325000
1!
b11111 )
b1101 '
1*
#330000
0!
0*
#335000
1!
b100000 )
b1110 '
1*
#340000
0!
0*
0#
0,
b11 4
#345000
1!
b100001 )
b1111 '
1*
0%
b11 3
b0 4
b11 .
#350000
0!
0*
1#
1,
b1 4
#355000
1!
b100010 )
b10011 (
1*
0&
1%
b1 3
1-
b10 4
1$
b1 .
#360000
0!
0*
#365000
1!
b100011 )
b10000 '
1*
1&
b10 3
b10 .
#370000
0!
0*
0#
0,
b11 4
#375000
1!
b100100 )
b10100 (
1*
0%
b11 3
0-
b0 4
0$
b11 .
#380000
0!
0*
#385000
1!
b100101 )
b10101 (
1*
0&
b0 3
1-
1$
b0 .
#390000
0!
0*
1#
1,
b1 4
#395000
1!
b100110 )
b10110 (
1*
1%
b1 3
0-
b10 4
0$
b1 .
#400000
0!
0*
#405000
1!
b100111 )
b10111 (
1*
1&
b10 3
1-
1$
b10 .
#410000
0!
0*
0#
0,
b11 4
#415000
1!
b101000 )
b11000 (
1*
0%
b11 3
0-
b0 4
0$
b11 .
#420000
0!
0*
1#
1,
b1 4
#425000
1!
b101001 )
b11001 (
1*
0&
1%
b1 3
1-
b10 4
1$
b1 .
#430000
0!
0*
#435000
1!
b101010 )
b10001 '
1*
1&
b10 3
b10 .
#440000
0!
0*
#445000
1!
b101011 )
b11010 (
1*
0-
0$
#450000
0!
0*
0#
0,
b11 4
#455000
1!
b101100 )
b10010 '
1*
0%
b11 3
b0 4
b11 .
#460000
0!
0*
1#
1,
b1 4
#465000
1!
b101101 )
b11011 (
1*
0&
1%
b1 3
1-
b10 4
1$
b1 .
#470000
0!
0*
#475000
1!
b101110 )
b10011 '
1*
1&
b10 3
b10 .
#480000
0!
0*
#485000
1!
b101111 )
b11100 (
1*
0-
0$
#490000
0!
0*
0#
0,
b11 4
#495000
1!
b110000 )
b10100 '
1*
0%
b11 3
b0 4
b11 .
#500000
0!
0*
#505000
1!
b110001 )
b11101 (
1*
0&
b0 3
1-
1$
b0 .
#510000
0!
0*
#515000
1!
b110010 )
b11110 (
1*
0-
0$
#520000
0!
0*
#525000
1!
b110011 )
b10101 '
