HW6/p5/tb_counter_compare.v
`timescale 1ns/1ps

module tb_counter_compare;
    reg CLK = 0;
    reg CLR = 0;
    
    // Outputs from p11_6 (combinational decoder)
    wire [0:7] S_L_comb;
    
    // Outputs from p11_7 (registered decoder)
    wire [0:7] S_L_reg;
    
    // Instantiate p11_6 (combinational decoder)
    Vr3bitctrdec_comb dut_comb (
        .CLK(CLK),
        .CLR(CLR),
        .S_L(S_L_comb)
    );
    
    // Instantiate p11_7 (registered decoder)
    Vr3bitctrdec_reg dut_reg (
        .CLK(CLK),
        .CLR(CLR),
        .S_L(S_L_reg)
    );
    
    // 10-ns clock (50 MHz)
    always #5 CLK = ~CLK;
    
    // VCD dump for waveform analysis
    initial begin
        $dumpfile("counter_compare.vcd");
        $dumpvars(0, tb_counter_compare);
    end
    
    // Stimulus
    initial begin
        
        // Initial reset
        CLR = 1;
        repeat(2) @(posedge CLK);
        CLR = 0;
        
        // Run for ~40 clock cycles (3-bit counter cycles every 8 clocks)
        repeat(40) @(posedge CLK);
        
        CLR = 1;
        @(posedge CLK);
        CLR = 0;
        
        // Run a few more cycles
        repeat(10) @(posedge CLK);
        
        $finish;
    end
    
endmodule

module Vr3bitctrdec_comb ( CLK, CLR, S_L );
    input CLK, CLR;
    output reg [0:7] S_L;
    reg [2:0] Q;
    integer i;
    
    always @ (posedge CLK) // Create the counter f-f behavior
        if (CLR) Q <= 3'd0;
        else Q <= Q + 1;
    always @ (Q) begin // Decode counter states to create outputs
        S_L = 8'b11111111;
        for (i=0; i<=7; i=i+1)
        if (i == Q) S_L[i] = 0;
    end
endmodule

module Vr3bitctrdec_reg ( CLK, CLR, S_L );
    input CLK, CLR;
    output reg [0:7] S_L;
    reg [2:0] Q;
    integer i;
    
    always @ (posedge CLK) begin
        if (CLR) Q <= 3'd0; // Create the counter f-f behavior
        else Q <= Q + 1;
        S_L <= 8'b11111111; // Default for outputs is negated
        for (i=0; i<=7; i=i+1) // Decode counter states to assert
        if (i == Q) S_L[i] <= 0; // one active-low output
    end
endmodule

HW6/p5/counter_compare.vcd
$date
    Dec  1, 2025  08:07:50
$end
$version
    TOOL:	xmsim(64)	18.09-s011
$end
$timescale
    1 ps
$end

$scope module tb_counter_compare $end
$var reg       1 !    CLK $end
$var reg       1 "    CLR $end
$var wire      8 #    S_L_comb [0:7] $end
$var wire      8 $    S_L_reg [0:7] $end

$scope module dut_comb $end
$var wire      1 %    CLK  $end
$var wire      1 &    CLR  $end
$var reg       8 '    S_L [0:7] $end
$var reg       3 (    Q [2:0] $end
$var integer  32 )    i $end
$upscope $end


$scope module dut_reg $end
$var wire      1 %    CLK  $end
$var wire      1 &    CLR  $end
$var reg       8 *    S_L [0:7] $end
$var reg       3 +    Q [2:0] $end
$var integer  32 ,    i $end
$upscope $end

$upscope $end

$enddefinitions $end
$dumpvars
0!
1"
bx #
bx $
0%
1&
bx '
bx (
bx )
bx *
bx +
bx ,
$end
#5000
1!
1%
b0 ,
b1 ,
b10 ,
b11 ,
b100 ,
b101 ,
b110 ,
b111 ,
b1000 ,
b0 +
b11111111 *
b0 (
b11111111 '
b0 )
b1111111 '
b1 )
b10 )
b11 )
b100 )
b101 )
b110 )
b111 )
b1000 )
b1111111 #
b11111111 $
#10000
0!
0%
#15000
1!
0"
0&
1%
b0 ,
b1 ,
b10 ,
b11 ,
b100 ,
b101 ,
b110 ,
b111 ,
b1000 ,
b1 +
b1111111 *
b1 (
b11111111 '
b0 )
b1 )
b10111111 '
b10 )
b11 )
b100 )
b101 )
b110 )
b111 )
b1000 )
b10111111 #
b1111111 $
#20000
0!
0%
#25000
1!
1%
b0 ,
b1 ,
b10 ,
b11 ,
b100 ,
b101 ,
b110 ,
b111 ,
b1000 ,
b10 +
b11111111 *
b10111111 *
b10 (
b11111111 '
b0 )
b1 )
b10 )
b11011111 '
b11 )
b100 )
b101 )
b110 )
b111 )
b1000 )
b11011111 #
b10111111 $
#30000
0!
0%
#35000
1!
1%
b0 ,
b1 ,
b10 ,
b11 ,
b100 ,
b101 ,
b110 ,
b111 ,
b1000 ,
b11 +
b11111111 *
b11011111 *
b11 (
b11111111 '
b0 )
b1 )
b10 )
b11 )
b11101111 '
b100 )
b101 )
b110 )
b111 )
b1000 )
b11101111 #
b11011111 $
#40000
0!
0%
#45000
1!
1%
b0 ,
b1 ,
b10 ,
b11 ,
b100 ,
b101 ,
b110 ,
b111 ,
b1000 ,
b100 +
b11111111 *
b11101111 *
b100 (
b11111111 '
b0 )
b1 )
b10 )
b11 )
b100 )
b11110111 '
b101 )
b110 )
b111 )
b1000 )
b11110111 #
b11101111 $
#50000
0!
0%
#55000
1!
1%
b0 ,
b1 ,
b10 ,
b11 ,
b100 ,
b101 ,
b110 ,
b111 ,
b1000 ,
b101 +
b11111111 *
b11110111 *
b101 (
b11111111 '
b0 )
b1 )
b10 )
b11 )
b100 )
b101 )
b11111011 '
b110 )
b111 )
b1000 )
b11111011 #
b11110111 $
#60000
0!
0%
#65000
1!
1%
b0 ,
b1 ,
b10 ,
b11 ,
b100 ,
b101 ,
b110 ,
b111 ,
b1000 ,
b110 +
b11111111 *
b11111011 *
b110 (
b11111111 '
b0 )
b1 )
b10 )
b11 )
b100 )
b101 )
b110 )
b11111101 '
b111 )
b1000 )
b11111101 #
b11111011 $
#70000
0!
0%
#75000
1!
1%
b0 ,
b1 ,
b10 ,
b11 ,
b100 ,
b101 ,
b110 ,
b111 ,
b1000 ,
b111 +
b11111111 *
b11111101 *
b111 (
b11111111 '
b0 )
b1 )
b10 )
b11 )
b100 )
b101 )
b110 )
b111 )
b11111110 '
b1000 )
b11111110 #
b11111101 $
#80000
0!
0%
#85000
1!
1%
b0 ,
b1 ,
b10 ,
b11 ,
b100 ,
b101 ,
b110 ,
b111 ,
b1000 ,
b0 +
b11111111 *
b11111110 *
b0 (
b11111111 '
b0 )
b1111111 '
b1 )
b10 )
b11 )
b100 )
b101 )
b110 )
b111 )
b1000 )
b1111111 #
b11111110 $
#90000
0!
0%
#95000
1!
1%
b0 ,
b1 ,
b10 ,
b11 ,
b100 ,
b101 ,
b110 ,
b111 ,
b1000 ,
b1 +
b11111111 *
b1111111 *
b1 (
b11111111 '
b0 )
b1 )
b10111111 '
b10 )
b11 )
b100 )
b101 )
b110 )
b111 )
b1000 )
b10111111 #
b1111111 $
#100000
0!
0%
#105000
1!
1%
b0 ,
b1 ,
b10 ,
b11 ,
b100 ,
b101 ,
b110 ,
b111 ,
b1000 ,
b10 +
b11111111 *
b10111111 *
b10 (
b11111111 '
b0 )
b1 )
b10 )
b11011111 '
b11 )
b100 )
b101 )
b110 )
b111 )
b1000 )
b11011111 #
b10111111 $
#110000
0!
0%
#115000
1!
1%
b0 ,
b1 ,
b10 ,
b11 ,
b100 ,
b101 ,
b110 ,
b111 ,
b1000 ,
b11 +
b11111111 *
b11011111 *
b11 (
b11111111 '
b0 )
b1 )
b10 )
b11 )
b11101111 '
b100 )
b101 )
b110 )
b111 )
b1000 )
b11101111 #
b11011111 $
#120000
0!
0%
#125000
1!
1%
b0 ,
b1 ,
b10 ,
b11 ,
b100 ,
b101 ,
b110 ,
b111 ,
b1000 ,
b100 +
b11111111 *
b11101111 *
b100 (
b11111111 '
b0 )
b1 )
b10 )
b11 )
b100 )
b11110111 '
b101 )
b110 )
b111 )
b1000 )
b11110111 #
b11101111 $
#130000
0!
0%
#135000
1!
1%
b0 ,
b1 ,
b10 ,
b11 ,
b100 ,
b101 ,
b110 ,
b111 ,
b1000 ,
b101 +
b11111111 *
b11110111 *
b101 (
b11111111 '
b0 )
b1 )
b10 )
b11 )
b100 )
b101 )
b11111011 '
b110 )
b111 )
b1000 )
b11111011 #
b11110111 $
#140000
0!
0%
#145000
1!
1%
b0 ,
b1 ,
b10 ,
b11 ,
b100 ,
b101 ,
b110 ,
b111 ,
b1000 ,
b110 +
b11111111 *
b11111011 *
b110 (
b11111111 '
b0 )
b1 )
b10 )
b11 )
b100 )
b101 )
b110 )
b11111101 '
b111 )
b1000 )
b11111101 #
b11111011 $
#150000
0!
0%
#155000
1!
1%
b0 ,
b1 ,
b10 ,
b11 ,
b100 ,
b101 ,
b110 ,
b111 ,
b1000 ,
b111 +
b11111111 *
b11111101 *
b111 (
b11111111 '
b0 )
b1 )
b10 )
b11 )
b100 )
b101 )
b110 )
b111 )
b11111110 '
b1000 )
b11111110 #
b11111101 $
#160000
0!
0%
#165000
1!
1%
b0 ,
b1 ,
b10 ,
b11 ,
b100 ,
b101 ,
b110 ,
b111 ,
b1000 ,
b0 +
b11111111 *
b11111110 *
b0 (
b11111111 '
b0 )
b1111111 '
b1 )
b10 )
b11 )
b100 )
b101 )
b110 )
b111 )
b1000 )
b1111111 #
b11111110 $
#170000
0!
0%
#175000
1!
1%
b0 ,
b1 ,
b10 ,
b11 ,
b100 ,
b101 ,
b110 ,
b111 ,
b1000 ,
b1 +
b11111111 *
b1111111 *
b1 (
b11111111 '
b0 )
b1 )
b10111111 '
b10 )
b11 )
b100 )
b101 )
b110 )
b111 )
b1000 )
b10111111 #
b1111111 $
#180000
0!
0%
#185000
1!
1%
b0 ,
b1 ,
b10 ,
b11 ,
b100 ,
b101 ,
b110 ,
b111 ,
b1000 ,
b10 +
b11111111 *
b10111111 *
b10 (
b11111111 '
b0 )
b1 )
b10 )
b11011111 '
b11 )
b100 )
b101 )
b110 )
b111 )
b1000 )
b11011111 #
b10111111 $
#190000
0!
0%
#195000
1!
1%
b0 ,
b1 ,
b10 ,
b11 ,
b100 ,
b101 ,
b110 ,
b111 ,
b1000 ,
b11 +
b11111111 *
b11011111 *
b11 (
b11111111 '
b0 )
b1 )
b10 )
b11 )
b11101111 '
b100 )
b101 )
b110 )
b111 )
b1000 )
b11101111 #
b11011111 $
#200000
0!
0%
#205000
1!
1%
b0 ,
b1 ,
b10 ,
b11 ,
b100 ,
b101 ,
b110 ,
b111 ,
b1000 ,
b100 +
b11111111 *
b11101111 *
b100 (
b11111111 '
b0 )
b1 )
b10 )
b11 )
b100 )
b11110111 '
b101 )
b110 )
b111 )
b1000 )
b11110111 #
b11101111 $
#210000
0!
0%
#215000
1!
1%
b0 ,
b1 ,
b10 ,
b11 ,
b100 ,
b101 ,
b110 ,
b111 ,
b1000 ,
b101 +
b11111111 *
b11110111 *
b101 (
b11111111 '
b0 )
b1 )
b10 )
b11 )
b100 )
b101 )
b11111011 '
b110 )
b111 )
b1000 )
b11111011 #
b11110111 $
#220000
0!
0%
#225000
1!
1%
b0 ,
b1 ,
b10 ,
b11 ,
b100 ,
b101 ,
b110 ,
b111 ,
b1000 ,
b110 +
b11111111 *
b11111011 *
b110 (
b11111111 '
b0 )
b1 )
b10 )
b11 )
b100 )
b101 )
b110 )
b11111101 '
b111 )
b1000 )
b11111101 #
b11111011 $
#230000
0!
0%
#235000
1!
1%
b0 ,
b1 ,
b10 ,
b11 ,
b100 ,
b101 ,
b110 ,
b111 ,
b1000 ,
b111 +
b11111111 *
b11111101 *
b111 (
b11111111 '
b0 )
b1 )
b10 )
b11 )
b100 )
b101 )
b110 )
b111 )
b11111110 '
b1000 )
b11111110 #
b11111101 $
#240000
0!
0%
#245000
1!
1%
b0 ,
b1 ,
b10 ,
b11 ,
b100 ,
b101 ,
b110 ,
b111 ,
b1000 ,
b0 +
b11111111 *
b11111110 *
b0 (
b11111111 '
b0 )
b1111111 '
b1 )
b10 )
b11 )
b100 )
b101 )
b110 )
b111 )
b1000 )
b1111111 #
b11111110 $
#250000
0!
0%
#255000
1!
1%
b0 ,
b1 ,
b10 ,
b11 ,
b100 ,
b101 ,
b110 ,
b111 ,
b1000 ,
b1 +
b11111111 *
b1111111 *
b1 (
b11111111 '
b0 )
b1 )
b10111111 '
b10 )
b11 )
b100 )
b101 )
b110 )
b111 )
b1000 )
b10111111 #
b1111111 $
#260000
0!
0%
#265000
1!
1%
b0 ,
b1 ,
b10 ,
b11 ,
b100 ,
b101 ,
b110 ,
b111 ,
b1000 ,
b10 +
b11111111 *
b10111111 *
b10 (
b11111111 '
b0 )
b1 )
b10 )
b11011111 '
b11 )
b100 )
b101 )
b110 )
b111 )
b1000 )
b11011111 #
b10111111 $
#270000
0!
0%
#275000
1!
1%
b0 ,
b1 ,
b10 ,
b11 ,
b100 ,
b101 ,
b110 ,
b111 ,
b1000 ,
b11 +
b11111111 *
b11011111 *
b11 (
b11111111 '
b0 )
b1 )
b10 )
b11 )
b11101111 '
b100 )
b101 )
b110 )
b111 )
b1000 )
b11101111 #
b11011111 $
#280000
0!
0%
#285000
1!
1%
b0 ,
b1 ,
b10 ,
b11 ,
b100 ,
b101 ,
b110 ,
b111 ,
b1000 ,
b100 +
b11111111 *
b11101111 *
b100 (
b11111111 '
b0 )
b1 )
b10 )
b11 )
b100 )
b11110111 '
b101 )
b110 )
b111 )
b1000 )
b11110111 #
b11101111 $
#290000
0!
0%
#295000
1!
1%
b0 ,
b1 ,
b10 ,
b11 ,
b100 ,
b101 ,
b110 ,
b111 ,
b1000 ,
b101 +
b11111111 *
b11110111 *
b101 (
b11111111 '
b0 )
b1 )
b10 )
b11 )
b100 )
b101 )
b11111011 '
b110 )
b111 )
b1000 )
b11111011 #
b11110111 $
#300000
0!
0%
#305000
1!
1%
b0 ,
b1 ,
b10 ,
b11 ,
b100 ,
b101 ,
b110 ,
b111 ,
b1000 ,
b110 +
b11111111 *
b11111011 *
b110 (
b11111111 '
b0 )
b1 )
b10 )
b11 )
b100 )
b101 )
b110 )
b11111101 '
b111 )
b1000 )
b11111101 #
b11111011 $
#310000
0!
0%
#315000
1!
1%
b0 ,
b1 ,
b10 ,
b11 ,
b100 ,
b101 ,
b110 ,
b111 ,
b1000 ,
b111 +
b11111111 *
b11111101 *
b111 (
b11111111 '
b0 )
b1 )
b10 )
b11 )
b100 )
b101 )
b110 )
b111 )
b11111110 '
b1000 )
b11111110 #
b11111101 $
#320000
0!
0%
#325000
1!
1%
b0 ,
b1 ,
b10 ,
b11 ,
b100 ,
b101 ,
b110 ,
b111 ,
b1000 ,
b0 +
b11111111 *
b11111110 *
b0 (
b11111111 '
b0 )
b1111111 '
b1 )
b10 )
b11 )
b100 )
b101 )
b110 )
b111 )
b1000 )
b1111111 #
b11111110 $
#330000
0!
0%
#335000
1!
1%
b0 ,
b1 ,
b10 ,
b11 ,
b100 ,
b101 ,
b110 ,
b111 ,
b1000 ,
b1 +
b11111111 *
b1111111 *
b1 (
b11111111 '
b0 )
b1 )
b10111111 '
b10 )
b11 )
b100 )
b101 )
b110 )
b111 )
b1000 )
b10111111 #
b1111111 $
#340000
0!
0%
#345000
1!
1%
b0 ,
b1 ,
b10 ,
b11 ,
b100 ,
b101 ,
b110 ,
b111 ,
b1000 ,
b10 +
b11111111 *
b10111111 *
b10 (
b11111111 '
b0 )
b1 )
b10 )
b11011111 '
b11 )
b100 )
b101 )
b110 )
b111 )
b1000 )
b11011111 #
b10111111 $
#350000
0!
0%
#355000
1!
1%
b0 ,
b1 ,
b10 ,
b11 ,
b100 ,
b101 ,
b110 ,
b111 ,
b1000 ,
b11 +
b11111111 *
b11011111 *
b11 (
b11111111 '
b0 )
b1 )
b10 )
b11 )
b11101111 '
b100 )
b101 )
b110 )
b111 )
b1000 )
b11101111 #
b11011111 $
#360000
0!
0%
#365000
1!
1%
b0 ,
b1 ,
b10 ,
b11 ,
b100 ,
b101 ,
b110 ,
b111 ,
b1000 ,
b100 +
b11111111 *
b11101111 *
b100 (
b11111111 '
b0 )
b1 )
b10 )
b11 )
b100 )
b11110111 '
b101 )
b110 )
b111 )
b1000 )
b11110111 #
b11101111 $
#370000
0!
0%
#375000
1!
1%
b0 ,
b1 ,
b10 ,
b11 ,
b100 ,
b101 ,
b110 ,
b111 ,
b1000 ,
b101 +
b11111111 *
b11110111 *
b101 (
b11111111 '
b0 )
b1 )
b10 )
b11 )
b100 )
b101 )
b11111011 '
b110 )
b111 )
b1000 )
b11111011 #
b11110111 $
#380000
0!
0%
#385000
1!
1%
b0 ,
b1 ,
b10 ,
b11 ,
b100 ,
b101 ,
b110 ,
b111 ,
b1000 ,
b110 +
b11111111 *
b11111011 *
b110 (
b11111111 '
b0 )
b1 )
b10 )
b11 )
b100 )
b101 )
b110 )
b11111101 '
b111 )
b1000 )
b11111101 #
b11111011 $
#390000
0!
0%
#395000
1!
1%
b0 ,
b1 ,
b10 ,
b11 ,
b100 ,
b101 ,
b110 ,
b111 ,
b1000 ,
b111 +
b11111111 *
b11111101 *
b111 (
b11111111 '
b0 )
b1 )
b10 )
b11 )
b100 )
b101 )
b110 )
b111 )
b11111110 '
b1000 )
b11111110 #
b11111101 $
#400000
0!
0%
#405000
1!
1%
b0 ,
b1 ,
b10 ,
b11 ,
b100 ,
b101 ,
b110 ,
b111 ,
b1000 ,
b0 +
b11111111 *
b11111110 *
b0 (
b11111111 '
b0 )
b1111111 '
b1 )
b10 )
b11 )
b100 )
b101 )
b110 )
b111 )
b1000 )
b1111111 #
b11111110 $
#410000
0!
0%
#415000
1!
1"
1&
1%
b0 ,
b1 ,
b10 ,
b11 ,
b100 ,
b101 ,
b110 ,
b111 ,
b1000 ,
b11111111 *
b1111111 *
b1111111 $
#420000
0!
0%
#425000
1!
0"
0&
1%
b0 ,
b1 ,
b10 ,
b11 ,
b100 ,
b101 ,
b110 ,
b111 ,
b1000 ,
b1 +
b11111111 *
b1111111 *
b1 (
b11111111 '
b0 )
b1 )
b10111111 '
b10 )
b11 )
b100 )
b101 )
b110 )
b111 )
b1000 )
b10111111 #
#430000
0!
0%
#435000
1!
1%
b0 ,
b1 ,
b10 ,
b11 ,
b100 ,
b101 ,
b110 ,
b111 ,
b1000 ,
b10 +
b11111111 *
b10111111 *
b10 (
b11111111 '
b0 )
b1 )
b10 )
b11011111 '
b11 )
b100 )
b101 )
b110 )
b111 )
b1000 )
b11011111 #
b10111111 $
#440000
0!
0%
#445000
1!
1%
b0 ,
b1 ,
b10 ,
b11 ,
b100 ,
b101 ,
b110 ,
b111 ,
b1000 ,
b11 +
b11111111 *
b11011111 *
b11 (
b11111111 '
b0 )
b1 )
b10 )
b11 )
b11101111 '
b100 )
b101 )
b110 )
b111 )
b1000 )
b11101111 #
b11011111 $
#450000
0!
0%
#455000
1!
1%
b0 ,
b1 ,
b10 ,
b11 ,
b100 ,
b101 ,
b110 ,
b111 ,
b1000 ,
b100 +
b11111111 *
b11101111 *
b100 (
b11111111 '
b0 )
b1 )
b10 )
b11 )
b100 )
b11110111 '
b101 )
b110 )
b111 )
b1000 )
b11110111 #
b11101111 $
#460000
0!
0%
#465000
1!
1%
b0 ,
b1 ,
b10 ,
b11 ,
b100 ,
b101 ,
b110 ,
b111 ,
b1000 ,
b101 +
b11111111 *
b11110111 *
b101 (
b11111111 '
b0 )
b1 )
b10 )
b11 )
b100 )
b101 )
b11111011 '
b110 )
b111 )
b1000 )
b11111011 #
b11110111 $
#470000
0!
0%
#475000
1!
1%
b0 ,
b1 ,
b10 ,
b11 ,
b100 ,
b101 ,
b110 ,
b111 ,
b1000 ,
b110 +
b11111111 *
b11111011 *
b110 (
b11111111 '
b0 )
b1 )
b10 )
b11 )
b100 )
b101 )
b110 )
b11111101 '
b111 )
b1000 )
b11111101 #
b11111011 $
#480000
0!
0%
#485000
1!
1%
b0 ,
b1 ,
b10 ,
b11 ,
b100 ,
b101 ,
b110 ,
b111 ,
b1000 ,
b111 +
b11111111 *
b11111101 *
b111 (
b11111111 '
b0 )
b1 )
b10 )
b11 )
b100 )
b101 )
b110 )
b111 )
b11111110 '
b1000 )
b11111110 #
b11111101 $
#490000
0!
0%
#495000
1!
1%
b0 ,
b1 ,
b10 ,
b11 ,
b100 ,
b101 ,
b110 ,
b111 ,
b1000 ,
b0 +
b11111111 *
b11111110 *
b0 (
b11111111 '
b0 )
b1111111 '
b1 )
b10 )
b11 )
b100 )
b101 )
b110 )
b111 )
b1000 )
b1111111 #
b11111110 $
#500000
0!
0%
#505000
1!
1%
b0 ,
b1 ,
b10 ,
b11 ,
b100 ,
b101 ,
b110 ,
b111 ,
b1000 ,
b1 +
b11111111 *
b1111111 *
b1 (
b11111111 '
b0 )
b1 )
b10111111 '
b10 )
b11 )
b100 )
b101 )
b110 )
b111 )
b1000 )
b10111111 #
b1111111 $
#510000
0!
0%
#515000
1!
1%
b0 ,
b1 ,
b10 ,
b11 ,
b100 ,
b101 ,
b110 ,
b111 ,
b1000 ,
b10 +
b11111111 *
b10111111 *
b10 (
b11111111 '
b0 )
b1 )
b10 )
b11011111 '
b11 )
b100 )
b101 )
b110 )
b111 )
b1000 )
b11011111 #
b10111111 $
